evernote_to_sqlite/__init__.py
evernote_to_sqlite/cli.py
evernote_to_sqlite/utils.py
evernote_to_sqlite-0.3.2.dist-info/LICENSE
evernote_to_sqlite-0.3.2.dist-info/METADATA
evernote_to_sqlite-0.3.2.dist-info/WHEEL
evernote_to_sqlite-0.3.2.dist-info/entry_points.txt
evernote_to_sqlite-0.3.2.dist-info/top_level.txt
evernote_to_sqlite-0.3.2.dist-info/RECORD
