Metadata-Version: 2.1
Name: evernote-to-sqlite
Version: 0.3.2
Summary: Tools for converting Evernote content to SQLite
Home-page: https://github.com/dogsheep/evernote-to-sqlite
Author: Simon Willison
License: Apache License, Version 2.0
Project-URL: Issues, https://github.com/dogsheep/evernote-to-sqlite/issues
Project-URL: CI, https://github.com/dogsheep/evernote-to-sqlite/actions
Project-URL: Changelog, https://github.com/dogsheep/evernote-to-sqlite/releases
Platform: UNKNOWN
Requires-Dist: click
Requires-Dist: sqlite-utils (>=3.0)
Provides-Extra: test
Requires-Dist: pytest ; extra == 'test'
